odoo8_addon_product_variant_supplierinfo-8.0.1.0.0.99.dev26-py3.8-nspkg.pth
odoo_addons/product_variant_supplierinfo/README.rst
odoo_addons/product_variant_supplierinfo/__init__.py
odoo_addons/product_variant_supplierinfo/__openerp__.py
odoo_addons/product_variant_supplierinfo/demo/procurement_demo.xml
odoo_addons/product_variant_supplierinfo/demo/product_demo.xml
odoo_addons/product_variant_supplierinfo/i18n/ca.po
odoo_addons/product_variant_supplierinfo/i18n/de.po
odoo_addons/product_variant_supplierinfo/i18n/el_GR.po
odoo_addons/product_variant_supplierinfo/i18n/es.po
odoo_addons/product_variant_supplierinfo/i18n/es_ES.po
odoo_addons/product_variant_supplierinfo/i18n/es_MX.po
odoo_addons/product_variant_supplierinfo/i18n/eu.po
odoo_addons/product_variant_supplierinfo/i18n/fi.po
odoo_addons/product_variant_supplierinfo/i18n/fr.po
odoo_addons/product_variant_supplierinfo/i18n/fr_CH.po
odoo_addons/product_variant_supplierinfo/i18n/fr_FR.po
odoo_addons/product_variant_supplierinfo/i18n/gl.po
odoo_addons/product_variant_supplierinfo/i18n/hr.po
odoo_addons/product_variant_supplierinfo/i18n/hr_HR.po
odoo_addons/product_variant_supplierinfo/i18n/it.po
odoo_addons/product_variant_supplierinfo/i18n/nl.po
odoo_addons/product_variant_supplierinfo/i18n/nl_NL.po
odoo_addons/product_variant_supplierinfo/i18n/product_variant_supplierinfo.pot
odoo_addons/product_variant_supplierinfo/i18n/pt.po
odoo_addons/product_variant_supplierinfo/i18n/pt_BR.po
odoo_addons/product_variant_supplierinfo/i18n/pt_PT.po
odoo_addons/product_variant_supplierinfo/i18n/ro.po
odoo_addons/product_variant_supplierinfo/i18n/ru.po
odoo_addons/product_variant_supplierinfo/i18n/sk.po
odoo_addons/product_variant_supplierinfo/i18n/sl.po
odoo_addons/product_variant_supplierinfo/i18n/tr.po
odoo_addons/product_variant_supplierinfo/i18n/tr_TR.po
odoo_addons/product_variant_supplierinfo/i18n/vi_VN.po
odoo_addons/product_variant_supplierinfo/i18n/zh_CN.po
odoo_addons/product_variant_supplierinfo/models/__init__.py
odoo8_addon_product_variant_supplierinfo-8.0.1.0.0.99.dev26.dist-info/METADATA
odoo8_addon_product_variant_supplierinfo-8.0.1.0.0.99.dev26.dist-info/WHEEL
odoo8_addon_product_variant_supplierinfo-8.0.1.0.0.99.dev26.dist-info/namespace_packages.txt
odoo8_addon_product_variant_supplierinfo-8.0.1.0.0.99.dev26.dist-info/top_level.txt
odoo8_addon_product_variant_supplierinfo-8.0.1.0.0.99.dev26.dist-info/RECORD
